CHANGELOG.txt
LICENCE.txt
MANIFEST.in
README.txt
__FOR FUTURE REFERENCE__.txt
requirements.txt
setup.py
codeless/__init__.py
codeless/fs.py
codeless/imb.py
codeless/olr.py
codeless/src.py
codeless/trans.py
codeless.egg-info/PKG-INFO
codeless.egg-info/SOURCES.txt
codeless.egg-info/dependency_links.txt
codeless.egg-info/requires.txt
codeless.egg-info/top_level.txt
codeless/encode/__init__.py
codeless/encode/nominal.py
codeless/encode/ordinal.py
codeless/impute/__init__.py
codeless/impute/cat.py
codeless/impute/num.py