Metadata-Version: 1.1
Name: codeless
Version: 0.0.5
Summary: A simple library to perform EDA & Data Engineering quickly without writing any code
Home-page: https://github.com/porky5191/CodelessLibrary
Author: Arun Kumar Nath
Author-email: arunnath792@gmail.com
License: MIT
Keywords: codeless
Platform: UNKNOWN
Classifier: Development Status :: 5 - Production/Stable
Classifier: Intended Audience :: End Users/Desktop
Classifier: Intended Audience :: Developers
Classifier: Intended Audience :: System Administrators
Classifier: Intended Audience :: Education
Classifier: Operating System :: Microsoft :: Windows :: Windows 10
Classifier: License :: OSI Approved :: MIT License
Classifier: Programming Language :: Python :: 3
